[
  {
    "question": "What is the capital of India?",
    "options": ["Mumbai", "New Delhi", "Kolkata", "Chennai"],
    "correct_answer": 1,
    "explanation": "New Delhi is the capital of India",
    "difficulty": "easy",
    "marks": 1,
    "negative_marks": 0.25
  },
  {
    "question": "What is 2 + 2?",
    "options": ["2", "3", "4", "5"],
    "correct_answer": 2,
    "explanation": "Basic arithmetic: 2 + 2 = 4",
    "difficulty": "easy",
    "marks": 1,
    "negative_marks": 0.25
  },
  {
    "question": "Who wrote Romeo and Juliet?",
    "options": ["Charles Dickens", "William Shakespeare", "Jane Austen", "Mark Twain"],
    "correct_answer": 1,
    "explanation": "William Shakespeare wrote Romeo and Juliet",
    "difficulty": "medium",
    "marks": 2,
    "negative_marks": 0.5
  },
  {
    "question": "What is the chemical symbol for water?",
    "options": ["H2O", "CO2", "O2", "N2"],
    "correct_answer": 0,
    "explanation": "Water is composed of hydrogen and oxygen (H2O)",
    "difficulty": "easy",
    "marks": 1,
    "negative_marks": 0.25
  },
  {
    "question": "What is the largest planet in our solar system?",
    "options": ["Earth", "Mars", "Jupiter", "Saturn"],
    "correct_answer": 2,
    "explanation": "Jupiter is the largest planet in our solar system",
    "difficulty": "medium",
    "marks": 2,
    "negative_marks": 0.5
  }
]
